{
  "as_of_years": [
    2012,
    2026
  ],
  "last_crawled_years": [
    2012,
    2013,
    2014,
    2015,
    2016,
    2017,
    2018,
    2019,
    2020,
    2021,
    2022,
    2023,
    2024,
    2025,
    2026
  ],
  "directory_pages_updated_to": {
    "2016": "18 June 2026",
    "2017": "18 June 2026",
    "2018": "18 June 2026",
    "2019": "18 June 2026",
    "2020": "18 June 2026",
    "2021": "18 June 2026",
    "2022": "18 June 2026",
    "2023": "18 June 2026",
    "2024": "18 June 2026",
    "2025": "18 June 2026",
    "2026": "18 June 2026",
    "2012": "18 June 2026",
    "2013": "18 June 2026",
    "2014": "18 June 2026",
    "2015": "18 June 2026"
  },
  "rows": 9836,
  "state_distribution": {
    "other_affected": 726,
    "in_force_as_made": 6882,
    "amended": 261,
    "revoked": 1953,
    "partially_revoked": 14
  },
  "gold_si_count": 7661,
  "gold_join_coverage_pct": 99.57,
  "gold_with_non_made_state": 1837,
  "source": "eISB Legislation Directory chronological tables (isbc/siYYYY_*.html)",
  "caveat": "Discovery/indexing only \u2014 verify the official eISB entry before legal reliance. Whole vs provision-level revocation is heuristic from the 'How Affected' column."
}